littleflow/__init__.py
littleflow/__main__.py
littleflow/compiler.py
littleflow/doc.py
littleflow/flow.py
littleflow/model.py
littleflow/parser.py
littleflow/runner.py
littleflow/utils.py
littleflow-0.12.0.dist-info/LICENSE
littleflow-0.12.0.dist-info/METADATA
littleflow-0.12.0.dist-info/WHEEL
littleflow-0.12.0.dist-info/top_level.txt
littleflow-0.12.0.dist-info/RECORD
