Metadata-Version: 2.1
Name: littleflow
Version: 0.12.0
Summary: A little flow language for workflows
Home-page: https://github.com/alexmilowski/littleflow
Author: Alex Miłowski
Author-email: alex@milowski.com
License: Apache License 2.0
License-File: LICENSE
Requires-Dist: lark
Requires-Dist: numpy
Requires-Dist: click
Requires-Dist: pyyaml
